LICENSE
README.md
setup.py
padroniza_telefone/__init__.py
padroniza_telefone/telefone.py
padroniza_telefone.egg-info/PKG-INFO
padroniza_telefone.egg-info/SOURCES.txt
padroniza_telefone.egg-info/dependency_links.txt
padroniza_telefone.egg-info/top_level.txt