Metadata-Version: 2.1
Name: padroniza-telefone
Version: 0.0.4
Summary: Standardizes phone to E164 standard
Home-page: UNKNOWN
Author: Tatianno Alves
Author-email: tferreiraalves@gmail.com
License: MIT License
Keywords: standardize phone E164
Platform: UNKNOWN
License-File: LICENSE
